splipy/__init__.py
splipy/basis.py
splipy/curve.py
splipy/curve_factory.py
splipy/py.typed
splipy/splinemodel.py
splipy/splineobject.py
splipy/state.py
splipy/surface.py
splipy/surface_factory.py
splipy/trimmedsurface.py
splipy/volume.py
splipy/volume_factory.py
splipy/io/__init__.py
splipy/io/g2.py
splipy/io/grdecl.py
splipy/io/master.py
splipy/io/ofoam.py
splipy/io/spl.py
splipy/io/stl.py
splipy/io/svg.py
splipy/io/threedm.py
splipy/templates/teapot.bpt
splipy/utils/NACA.py
splipy/utils/__init__.py
splipy/utils/bisect.py
splipy/utils/curve.py
splipy/utils/image.py
splipy/utils/nutils.py
splipy/utils/refinement.py
splipy/utils/smooth.py
splipy-1.10.1.dist-info/METADATA
splipy-1.10.1.dist-info/WHEEL
splipy-1.10.1.dist-info/licenses/COPYING
splipy-1.10.1.dist-info/RECORD
