Metadata-Version: 2.4
Name: splipy
Version: 1.10.1
Summary: Spline modelling library for Python
Author-email: Kjetil Andre Johannessen <kjetil.johannessen@sintef.no>, Eivind Fonn <eivind.fonn@sintef.no>
License-File: COPYING
Requires-Python: <4.0,>=3.11
Requires-Dist: numpy>=1.25
Requires-Dist: scipy>=1.10
Requires-Dist: splipy-core
